{
  "name": "Non-Compete Agreement (NCA)",
  "description": "A restrictive covenant preventing an employee or contractor from competing with the company for a specified period within a certain geographic area.",
  "price": 10,
  "language": "en",
  "slug": "non-compete-agreement-nca",
  "content": "<h3 style='text-align:center;'>NON-COMPETE AGREEMENT</h3>\n<p>This Non-Compete Agreement (the \"Agreement\") is entered into as of {{formatDate agreement_date}} by and between <strong>{{company_name}}</strong> (the \"Company\") and <strong>{{contractor_name}}</strong> (the \"Contractor/Employee\"), in connection with the {{relationship_type}} existing between the Parties.</p>\n\n<p><strong>1. THE PARTIES</strong></p>\n<p><strong>Company:</strong> {{company_name}}, Address: {{company_address}}</p>\n<p><strong>Contractor/Employee:</strong> {{contractor_name}}, Address: {{contractor_address}}</p>\n\n<p><strong>2. NON-COMPETE COVENANT</strong></p>\n<p>The Contractor/Employee agrees that during the term of their relationship with the Company and for a period of <strong>{{duration}}</strong> following the termination of that relationship, they shall not, directly or indirectly, engage in, work for, consult with, or establish a business that competes with the Company's primary business of <strong>{{industry_field}}</strong>.</p>\n<p>This restrictive covenant shall apply within the geographic area of <strong>{{geographic_scope}}</strong>.</p>\n\n<p><strong>3. CONFIDENTIALITY AND NON-SOLICITATION</strong></p>\n<p>The Contractor/Employee further agrees not to solicit or attempt to solicit any clients, customers, or current employees of the Company for the duration specified above. Furthermore, the Contractor/Employee shall maintain the strict confidentiality of all trade secrets, client lists, and proprietary business information belonging to the Company indefinitely.</p>\n\n<p><strong>4. BREACH AND LIQUIDATED DAMAGES</strong></p>\n{{#if (eq liquidated_damages_apply 'Yes')}}\n<p>The Parties agree that a breach of this Agreement would cause irreparable harm to the Company. Therefore, in the event of a breach, the Contractor/Employee shall be liable to pay the Company the sum of <strong>{{penalty_amount}}</strong> as liquidated damages. The payment of liquidated damages does not preclude the Company from seeking injunctive relief or additional actual damages in a court of law.</p>\n{{else}}\n<p>In the event of a breach or threatened breach of this Agreement, the Company shall be entitled to seek injunctive relief to prevent such breach, in addition to pursuing any other legal or equitable remedies available for damages incurred.</p>\n{{/if}}\n\n<p><strong>5. GOVERNING LAW AND SEVERABILITY</strong></p>\n<p>This Agreement shall be governed by the laws of <strong>{{jurisdiction}}</strong>. If any provision, duration, or geographic scope within this Agreement is found to be unreasonable or unenforceable by a court of competent jurisdiction, such provision shall be modified to the maximum extent permitted by law rather than voided entirely.</p>\n\n<p>IN WITNESS WHEREOF, the Parties have executed this Non-Compete Agreement as of the date first above written.</p>\n\n<div style='margin-top: 40px; display: flex; justify-content: space-between; flex-wrap: wrap;'>\n <div style='margin-bottom: 20px;'><p><strong>For the Company</strong><br/><span style='display: inline-block; margin-top: 5px;'>{{company_name}}</span><br/><br/><span style='display: inline-block; margin-top: 15px;'>Signature: _________________________</span></p></div>\n <div style='margin-bottom: 20px;'><p><strong>Contractor/Employee</strong><br/><span style='display: inline-block; margin-top: 5px;'>{{contractor_name}}</span><br/><br/><span style='display: inline-block; margin-top: 15px;'>Signature: _________________________</span></p></div>\n</div>",
  "fields": [
    { "name": "company_name", "label": "Company Name", "fieldType": "text", "required": true },
    { "name": "company_address", "label": "Company Address", "fieldType": "textarea", "required": true },
    { "name": "contractor_name", "label": "Contractor / Employee Name", "fieldType": "text", "required": true },
    { "name": "contractor_address", "label": "Contractor / Employee Address", "fieldType": "textarea", "required": true },
    { "name": "relationship_type", "label": "Type of Relationship", "fieldType": "text", "placeholder": "e.g., Employment Agreement, Consulting Agreement", "required": true },
    { "name": "duration", "label": "Duration of Non-Compete (After termination)", "fieldType": "text", "placeholder": "e.g., 12 Months, 2 Years", "required": true },
    { "name": "geographic_scope", "label": "Geographic Scope (Restricted Area)", "fieldType": "text", "placeholder": "e.g., State of New York, 50-mile radius of HQ", "required": true },
    { "name": "industry_field", "label": "Industry / Restricted Field", "fieldType": "text", "placeholder": "e.g., E-commerce Logistics, Real Estate Brokerage", "required": true },
    { "name": "liquidated_damages_apply", "label": "Include Liquidated Damages (Penalty) Clause?", "fieldType": "radio", "options": ["Yes", "No"], "required": true },
    { "name": "penalty_amount", "label": "Penalty Amount (Include Currency)", "fieldType": "text", "placeholder": "e.g., $10,000", "required": false, "condition": { "field": "liquidated_damages_apply", "value": "Yes" } },
    { "name": "jurisdiction", "label": "Governing Law / Jurisdiction", "fieldType": "text", "placeholder": "e.g., State of California, UK Law", "required": true },
    { "name": "agreement_date", "label": "Date of Agreement", "fieldType": "date", "required": true },
    { "name": "document_email", "label": "Email (For delivery)", "fieldType": "email", "required": true }
  ],
  "isActive": true,
  "isSystem": true
}